pollux_framework/__init__.py
pollux_framework/abstract/__init__.py
pollux_framework/abstract/databasedriver_abstract.py
pollux_framework/abstract/unit_abstract.py
pollux_framework/abstract/unit_module_abstract.py
pollux_framework/app.py
pollux_framework/database/__init__.py
pollux_framework/database/csv_driver.py
pollux_framework/database/influxdb_csv_connector.py
pollux_framework/database/influxdb_driver.py
pollux_framework/framework/__init__.py
pollux_framework/framework/boot_plant.py
pollux_framework/framework/loop.py
pollux_framework/framework/mainmodule.py
pollux_framework/framework/plant.py
pollux_framework/modules/__init__.py
pollux_framework/modules/electrolyser/unit.py
pollux_framework-0.1.0.dist-info/METADATA
pollux_framework-0.1.0.dist-info/WHEEL
pollux_framework-0.1.0.dist-info/RECORD
